app/__init__.py
app/__main__.py
app/funcmodule.py
secretKeeper-0.0.1.dist-info/LICENSE
secretKeeper-0.0.1.dist-info/METADATA
secretKeeper-0.0.1.dist-info/WHEEL
secretKeeper-0.0.1.dist-info/entry_points.txt
secretKeeper-0.0.1.dist-info/top_level.txt
secretKeeper-0.0.1.dist-info/RECORD
