Metadata-Version: 2.1
Name: secretKeeper
Version: 0.0.1
Summary: A simple password manager to be used with Good-Bot.
Home-page: UNKNOWN
Author: Tricky
License: MIT
Platform: UNKNOWN
